{
  "id": "doc_20251217_141710_chunk_268",
  "text": "lanetary patterns, which promise an independent occupation\nand a busi'less career. of course. with the concurrence of other factors\nwe have -enumerated in the chapter on the Lag.na the Olandra·lagna,\nthe Surya (Sun), the Buddha (Mercury). the Shani (Saturn) and the\nGuru (J upitef), are described as under:\nThe Lagna. the Chandra·lagna and the four planetary significators\nare at lea.st normal in strength. At the same time five Planets or more\nate placed in the 10tt~. 11~~'~. 121h. P1 , 2nd and/ or 3~ houses from the\ntagna or the Chandra·lagna. It can be safely asserted that the horoscope\nIn question ptesents a person who Is designed for an Independent\noccupation and a business career. The five Planets which are to occupy\nthe houses mentioned above may include any of the planetary significators\n\n102 Encydopeda ofVedicAst!OIOgy: Yout PtOftJSSiOtt\nof the occupation. More than the five Planets well placed in the houses\nmentioned above improve the qualifications of the horoscope to",
  "metadata": {
    "source": "ENCYCLOPEDIA-OF-VEDIC-ASTROLOGY - English.pdf",
    "file_type": ".pdf",
    "file_hash": "ef108f09051687c9017d6d977a95565e27de64804973faa10c496544e09b2cd2"
  },
  "chunk_index": 268
}