{
  "id": "doc_20251217_141710_chunk_619",
  "text": "are effective. a man bom in poverty will become a king\nand a person born in rich families will become an emperor. The above\nproposition makes it dear that it is difficult to predict the nature of the\nfamily in which a person takes his birth. Now we shall take a few\nhoroscopes and see how far these Yo93s are effeaive in the light of\nthe Oasas the natives may enjoy.\nChart No.:- Born on 8-8-1912 at 7-2S p.m .. at Bangalore.\nBalance of Mars Dasa : 6 years. 2 months and day.\n\n23$ Encydopeda ofVedicAst!OIOgy: Yout PtOftJSSiOtt\nideal position. Jupiter Oasa operated from 9-10·1936 to 9·10·1952.\nWhen Ju pl er Oasa began the native had started from the scratch but\nbefore the oasa concluded, he had established and organisation\nemploying several peoplE! and built himself up into an institutiott Further\nJupiter is lord of finances and gains. He acquired a tine house and vehicles.\nSatum's Oasa will end by about 1971. He is lord of L.ag.na aspected\nby Jupiter.",
  "metadata": {
    "source": "ENCYCLOPEDIA-OF-VEDIC-ASTROLOGY - English.pdf",
    "file_type": ".pdf",
    "file_hash": "ef108f09051687c9017d6d977a95565e27de64804973faa10c496544e09b2cd2"
  },
  "chunk_index": 619
}