{
  "id": "doc_20251217_142609_chunk_441",
  "text": "siderably afflicted, the former\nbeing associated with three malefics Sun, Mercury and\nMoon and aspected by Mars and the latter being aspected\nby Mars. From Chandra Lagna, the situation of Rahu in the\n5th being aspected by Mars suggests some miscarriages\nand premature births.\nInnumerable rules have been given in ancient works to\nascertain the number of issues, and losses and survivals\namong them. I do not propose to expand these in the\n\n240 How to Judge a Horoscope\nChart No. 104.—Born on 11-4-1907 at 6-50 p.m.\n(l.S.T.) (Lat. 11° 15' N., Long. 75° 45' E.)\nBalance of Saturn Dasa at birth : Years 3-2-6.\npages of this book. I shall give a few typical illustrations\nand the intelligent reader can study such charts in the light\nof principles which may be gathered from any standard\nastrological works. Usually the number of children to be\nborn is guessed by the number of Navamsas gained by the\n5th house or 5th lord. If the 5th lord is aspected by Jupiter\nor Venus, the number is doubled.",
  "metadata": {
    "source": "raman-how-to-judge-horoscope-1.pdf",
    "file_type": ".pdf",
    "file_hash": "4ed86aac6723314ad2e1d34f43c8d1267ece51d442abd301ea9789980d250404"
  },
  "chunk_index": 441
}