{
  "id": "doc_20251217_142023_chunk_728",
  "text": "un through the 5th Saturn through the 1st house,\nand Mercury through the 4th. there is every likelihood of loss of\nwealth and honour, and death.\n\\'ak 'atro-Gocara Connected with the subject of Gocara\nor planetary transits there is a method of finding out whether a\nparticular period is favourable or not. This is done by noting\nthe nature of the star occupied by the Sun m transit and its\n\nTRANSITS 251\nrelationship with one's natal asterism and some other stars which\nbear close kinship with that. For this purpose a diagram is\nneeded, which is called the Saptasaldka-Cakra. In this figure\nwhat you have to do is that you should draw seven horizontal\nlines and seven vertical lines crossing the previous ones. While\ndrawing the lines see that the ends of all the lines jut out so that\nyou may get 28 points. In this scheme there is one more asterism\ncalled Abhijit which comes in between Uttarasadha and Sravana,\nThe first asterism that should be written at the point in the",
  "metadata": {
    "source": "jyotish_fundamentals-of-astrology_m-ramakrishna-bhat-1.pdf",
    "file_type": ".pdf",
    "file_hash": "e5a3ea7f4ad4e2c7aeff1f8011d280a31b7a004a2d13ffd77e1158a8d2169388"
  },
  "chunk_index": 728
}