{
  "id": "doc_20251217_142044_chunk_19",
  "text": "igns occu\npied by the lord oflagna and by the Moon can be the lagna at\nbirth. This is a vague theory. lt can at best help us when the\ncalculated lagna is at the beginning or at the end of a sign.\nVII. There is still another view. Take the navamsa sign of\nthe lagna. It has 200 minutes, duration. Find the dvadasamsa\nof that navamsa sign. Each dvadasamsa has duration of 16\nminutes and 40 seconds. Count the resultant dvadasamsa\nfrom the navamsa lagna. If it falls in an odd sign like Mesha,\nVrishabha etc., the native is a male.\nEach dvadasamsa of the navamsa lagna is of 16' .40\" dura\ntion. When the lagna is 25 deg.46' of Pisces, the navamsa\nlagna is Kumbha. In the eighth navamsa 146 minutes are\nover. This gives the ninth dvadasamsa. It is Tula, an odd sign.\nThis agrees with the sex of the native. But if the ayanamsa\nvalue given by Lahiri is not accepted, the result can be differ\nent. This method can fix the lagna and not the time of birth.",
  "metadata": {
    "source": "Jyotish_Rectification of birth time.pdf",
    "file_type": ".pdf",
    "file_hash": "e3f66555b37975481f13236f3e65ee560be190925d18dda6390da58985348956"
  },
  "chunk_index": 19
}