{
  "id": "doc_20251217_141853_chunk_62",
  "text": "efvlekeÀb DeeosM³eced ~~ 10 ~~\nDeLe JeenveefJejece³eesieew le®íeefvlekeÀjCeb ®een ~ ³eeJevle Fefle ~ $etÀje\nFl³eveg<e²: ³eeJevle: JeenvemLee: MegYeefJenie¢Meeb iees®eje veesYeJes³eg: MegYeûen ¢äde ve\nm³eg: leeJevlees ve=Ceeb HejceiegCeJeleeb Òeke=ÀäiegCe³egÊeÀeveeb Jeenveeveeb efJejecee: efJeveeMee:\nm³eg: ~\nDeLe ÜeoMeeäceielee: $etÀje: ³eeJevle Fl³eveg<e²M®elegLe¥ HeM³eefvle ®esÊeoe\nHeefC[lewmleÜosJe ¢ä $etÀjûens me±îeeÒee³es mJeJeenveeveeb efJejecee: m³egefjefle %es³eced ~ le$e\nJeenveeveeb MegYekeÀjCeb MeeefvlekebÀ Òee%ew: DeeosM³eb efJeOes³eefceefleMes<e: ~~\nFefle®elegLe&YeeJe:~~ 10 ~~\nefnvoerö MegYeûen keÀer ¢ef<ì mes Jebef®ele efpeleves HeeHeûen ®elegLe& YeeJe ceW jnW\nGleves ner JeenveeW keÀe veeMe neslee nw ~ ÜeoMe Deewj DeäceYeeJe ceW efpeleves HeeHeûen\nefmLele neskeÀj ®elegLe& YeeJe keÀes osKeW Gleves mebK³ekeÀ De®ís JeenveeW keÀe veeMe neslee nw ~\nSsmee og³eexie nesves Hej mece³eevegmeej Jeenve nsleg MegYe Meevl³eLe& ke=Àl³e keÀe DeeosMe",
  "metadata": {
    "source": "Jataka-Alankar - Hindi.pdf",
    "file_type": ".pdf",
    "file_hash": "b11d368369b4403d20f3042032e1fe6f7df0394e35a6b53112f2de19b5fd2b62"
  },
  "chunk_index": 62
}