{
  "id": "doc_20251217_141446_chunk_158",
  "text": "4\npied by Mars. Mercury only Sun\nhelps Sun and Venus in their Jup L Mar Ven\nMer\ncruel work. Ketu too is\nthrowing its cruel aspect 5th Ket\non the 3rd house. With such Moon\na heavy killing inlluence on\n'i'','\nthe 3rd house, little doubt Rah\narises that the father of the\nnative had to marry three\nSat\ntimes.\nHere is Birth Chart lO of Aries ascendant. Here again\nMercur5/, lord of the 3rd\nL house as representative of\nMoon\nKet the wife of father suffers,\nleading to two marriages of\nfather. Mark that a strong\nand exalted Mars fully as-\nMar\npects Ketu with the result\nVen\nthat the aspect of Ketu has in\nJup\nSun tt the addttional killing ef-\nRah\nMer ferts of Mars. Now Ketu fully\nSat\naspects Mercury, lord of the\n3rd house. It would also be seen that the role of Saturn\nis no less cruel. Betng the lord of the sign occupied by\nMars it acts as Mars and therefore. kills the 3rd house\nand its lord, whlch it influences. In short the killtng\nlnlluence of Mars and Ketu on the 3rd house and its lord",
  "metadata": {
    "source": "00 sapta-rishi-nadi-by-j-n-bhasin.pdf",
    "file_type": ".pdf",
    "file_hash": "51b505db6c1668509e59fbb3edf1c032ab489058716a0caf176c648d0de82d08"
  },
  "chunk_index": 158
}