{
  "id": "doc_20251217_142310_chunk_90",
  "text": "The portion, that expired in Lagna is indicative of the content, to which\nthe wick has burnt already. The quantity of oil in the lamp will correspond to the waxing, or\nwaning state of the Moon.\n26-27. There were many lights, if the Sun is aspected by Mars. Should other planets be all weak,\nlight was obtained by burning grass. Should the Moon be in a Navansa of Saturn, or be in\nwatery Navansa, or in the 4th House and be in aspect to, or in the company of Saturn,\ndelivery was in a place of darkness. There is no doubt about this.\n28-30. Should the Ascendant be without the aspect of the Moon, the birth is behind the father, i.e.\nthe father was absent from the place. If the Sun is in the 9th identical with a Movable Rasi, the\nfather was in a foreign place. The Sun in the case of day birth and Saturn in the case of night\nbirth, if aspected by Mars, delivery is out of fathers sight. If the said Sun, or Saturn be in a\nMovable Sign, death of father (in a distant place) should be declared.",
  "metadata": {
    "source": "kalyana-varma-saravali.pdf",
    "file_type": ".pdf",
    "file_hash": "39c2ba173fa4c9ca019b47aee35eb3d9c19f61e61f5cfea2f54eb50e0d244f58"
  },
  "chunk_index": 90
}