{
  "id": "doc_20251217_141844_chunk_42",
  "text": "keÀeK³eb ieg©owJeleb ®e ~~“\nDeLe&öyegOe keÀer jeefMe (efceLegve) jeng keÀe G®®e, leLee ieg© keÀer jeefMe (Oeveg)\nkesÀleg keÀe G®®e nw ~ efkeÀvleg FmekeÀes ®ejoMeeve³eve ceW ueesie veneR ceeveles nQ ~\nmeJee&Le&ef®evleeceefCe ceW ye=nmHeefle, Meg$eÀ, Meefve ³es leerveeW jeng leLee kesÀleg kesÀ\nefce$e keÀns ie³es nQ ~ ³eLeeö\n``jenesmleg efce$eeefCe keÀJeerp³ecevoe: keÀsleesmleLewJee$e Jeoefvle lep%ee: ~“ Fefle ~~\nFme ÒekeÀej jeng kesÀleg kesÀ ie=n, G®®e Deeefo ceW celeYeso nQ ~ efkeÀvleg Deleerefvê³e\n%es³eefJe<e³e ceW ³egefÊeÀ kegÀí keÀece veneR osleer Fme efueS Jeneb Je=×JeekeÌ³e ner ÒeceeCe nw ~\nkeÀne Yeer nwõ\n``p³eewefle<eceeieceMeem$eb efJeÒeefleHeÊeew ve ³eesi³ecemceekeÀced ~\nmJe³ecesJe efJekeÀuHeef³elegb efkeÀvleg yentveeb celeb Je#³es ~~“ Fefle ~\nDeLe meeceev³esve ®ejoMeeJe<e&ieCevee$eÀceceenõ\nÒee®eerJe=efÊeefJe&<eceYes<eg ~~ 26~~ HejeJe=l³eesÊejs<eg ~~ 27~~\nJ³eeK³ee:- efJe<eceYes<eg ces<eefceLegveeefoefJe<ecejeefMe<eg Òee®eerJe=efÊe: $eÀceieCevee",
  "metadata": {
    "source": "Jaiminisutram.pdf",
    "file_type": ".pdf",
    "file_hash": "3137f73be46c3a6cfe4009a4bf6b65acc88983874fdbfe10cfde20b5eacf69c2"
  },
  "chunk_index": 42
}