{
  "id": "doc_20251217_142310_chunk_183",
  "text": "bsolute) celibacy.\n31. The religious order belonging to the Moon attracts the following various persons: Those\ndisciples, who smear their bodies with sacred ashes, those, who worship the Feet of Lord\nShiva, those, who are abandoned by the society, those, who are devoted to Bhagavati, those,\nwho give up company of others, those, who take to Soma Siddhanta and those, who carry\nbowls in their hands (for begging alms).\n32. The Buddhist monks, the tonsured, those, who wear white apparels, those, who beg wearing\ngood robes, those, who wear blood-red clothes and those, that have conquered their five\nsenses-all these mendicants are ruled by Mars.\n33. Mercury denotes an alm-seeker, a conjurer, a snake poison curer and one, who eats the flesh\nof a peacock.\n34. The ascetics ruled by Jupiter are: those, who hold a single sceptre (or mace), those, who hold\nthree sceptres, those, who wear red coloured apparels, those, who are in the third stage of",
  "metadata": {
    "source": "kalyana-varma-saravali.pdf",
    "file_type": ".pdf",
    "file_hash": "39c2ba173fa4c9ca019b47aee35eb3d9c19f61e61f5cfea2f54eb50e0d244f58"
  },
  "chunk_index": 183
}