{
  "id": "doc_20251217_142552_chunk_45",
  "text": "anger from\nforeign trade/travel. Thesepeople willhavedanger from\nlearned people/religion and also danger in forest/isolation.\nlearned people/religionandalsodangerinforest/isolation.\nRR aa hh uu iin\nn\nCC aa pp rr ii cc oo rr nn -- PP ee oo pp ll ee bb oo rrn\nn\nww ii tth\nh\nR Raa hh uu iin\nn\nCC aa pp rr ii cc oo rr nn\nwill take birth in a house which is situated in the South part of\nwilltakebirthinahousewhichissituated inthe Southpartof\nthe TownlVillage with a main-door towards the South. and\ntheTown/Villagewithamain-doortowardsthe South, and\nthe lane/road in front of the birth house runs from South to\nthe lane/road infrontofthebirthhouserunsfromSouthto\nNorth. These people will have weak knees or problems in\nNorth. Thesepeoplewillhaveweakkneesorproblemsin\nthe knees. These people have been cursed by their father in\nthe knees. Thesepeople havebeencursedbytheirfatherin\ntheir last life. These people may face trouble from a local\ntheirlastlife. Thesepeoplemay facetroublefromalocal",
  "metadata": {
    "source": "Rahu-Ketu-in-Brighu-Nadi-Astrology.pdf",
    "file_type": ".pdf",
    "file_hash": "2cd8f78ac7d17b22c534fcf701f00643d1c736bb0835d9467f5370e81413346f"
  },
  "chunk_index": 45
}