{
  "id": "doc_20251217_141823_chunk_690",
  "text": "places are Rekhapradas and are\nauspicious.\n43-45. The sage said. Now I will describe the auspicious Bhavas for the\nbenefit of the Acharyas. In the AshtakaVarg of Sūrya: Śani, Mangal and\n\nnd th st th\nSūrya in the 2 , 8 and 1 ; Guru and Budh in the 5 ; Budh, Candr and\nrd th\nLagn in the 3 ; Lagn, Sūrya, Śani and Mangal in the 4 ; Lagn, Sūrya, Śani,\nth\nMangal, Budh and Candr in the 10 ; Sūrya, Candr, Mangal, Budh, Guru,\nth th\nŚani and Lagn in the 11 ; Lagn, Śukr and Budh in the 12 ; Lagn, Śukr,\nth th\nBudh, Guru and Candr in the 6 ; Sūrya, Mangal, Śani and Śukr in the 7 ;\nth\nSūrya, Mangal, Śani, Budh and Guru in the 9 from their own places are\nRekhapradas.\nst\n46-48. In the AshtakaVarg of Candr: Budh, Candr and Guru in the 1 ; Guru\nnd\nand Mangal in the 2 ; Budh, Sūrya, Candr, Mangal, Śani, Śukr and Lagn in\nrd th\nthe 3 ; Guru, Śukr and Budh in the 4 ; Mangal, Budh, Śukr and Śani in the\nth th\n5 ; Sūrya, Candr, Mangal, Śani and Lagn in the 6 ; Sūrya, Candr, Guru,\nth th",
  "metadata": {
    "source": "instapdf.in-brihat-parashara-hora-shastra-book-710.pdf",
    "file_type": ".pdf",
    "file_hash": "40f12d7c6b42a7625d36bc1cc38576427f4c64f41a8f1353f4945a603a4397ba"
  },
  "chunk_index": 690
}