{
  "id": "doc_20251217_142609_chunk_43",
  "text": "elaborately discussed in the second part of this book to be\npublished in due course.\n\n4. Concerning the First House\nIn the delineation of any house, it is the Bhava that is\nimportant and not the Rasi. The difference between the Rasi\nand Bhava is explained in my books on Mathematical\nAstrology*. The Navamsa is also equally important. The\neffects of the Navamsa during which a person happens to be\nborn are supposed to influence all his activities throughout\nlife, subject to modifications according to the aspects of\nplanets situated at different piaces with reference to the\nNavamsa. It is the pivot on which the horoscope revolves.\nConsequently Hindu Astrology attaches the greatest\nimportance to the Navamsa chart. Every combination\nmentioned should be applied to the Rasi, Bhava and\nNavamsa charts and then a conclusion drawn. Essentials of\njudgement have been described in my other works and it\nwould be sheer waste of space if they were repeated here.",
  "metadata": {
    "source": "raman-how-to-judge-horoscope-1.pdf",
    "file_type": ".pdf",
    "file_hash": "4ed86aac6723314ad2e1d34f43c8d1267ece51d442abd301ea9789980d250404"
  },
  "chunk_index": 43
}