{
  "id": "doc_20251217_141947_chunk_1054",
  "text": "hese have been detailed in my Paper, \"Fertilizers in\nAncient India\" read in the International Sanskrit Conference, New\nDelhi, on 27-3-1972,\nSince tanks and the like do not look charming without shade\non their sides, one ought to have gardens laid out on the banks of\nwater.\n[Vide LIV. 119 where the author has spoken of the necessity\nfor shading the banks of tanks. Both the tanks and gardens are\nmutually beneficial. That is why charming gardens like the Brinda-\nvan Gardens in Mysore have been created near dams and reser-\nvoirs in modern India.\nThe metre upto 18th verse is or sloka,]\nNext he speaks of the Sesamum-treatment for the soil,\n^r: i\n•jfrtdiwiw Hd: m\\\\\n\n528 Brhat Samhitd\nA soft soil is helpful for all varieties of trees. First of all one\nought to sow there sesamum, which must be crushed when in bloom\n(to mix with the soil). This is the first treatment to be done for\nthe soil,\n[The sesamum plants in bloom, when cut into pieces and",
  "metadata": {
    "source": "jyotish_brihat-samhita_m-r-bhat_part-1-of-2_1981.pdf",
    "file_type": ".pdf",
    "file_hash": "f4c82cf5baeeeabcc4dd02e234a68437e6b98d6204707f7d4c3b46dbb79e5a94"
  },
  "chunk_index": 1054
}