{
  "id": "doc_20251217_142044_chunk_192",
  "text": "no such obligations;\nand Woodrow Wilson is a good example, for he was swept\nalong by destiny himself being never sensitive to anything of\nthat kind. The sixth house, therefore, on the analogy of the\ntwelfth points to the relationship that is hidden or limited -\nservant, relations, debts, etc. It implies the service he is to\nrender to his own affairs by way of work or sickness. Wilson\nhad a planet in the sixth, as a result of which he always failed\nin adjusting himself to others around him. The eighth, as\nusual, speaks of the expanding possibilities of these relations,\nlegacies and the means. It speaks of the development of char\nacter arising out of human relations, and of death, which is\nthe final chapter in this regeneration. The help one can render\nand the help one receives are given out here. Wilson and the\nQueen have planets here, and the part played by reciprocal\nactivity in their lives is too well-known.\n\n7\nDirections: Limitations\nPrognostication",
  "metadata": {
    "source": "Jyotish_Rectification of birth time.pdf",
    "file_type": ".pdf",
    "file_hash": "e3f66555b37975481f13236f3e65ee560be190925d18dda6390da58985348956"
  },
  "chunk_index": 192
}