{
  "id": "doc_20251217_141947_chunk_687",
  "text": "ash of arms. One having more than\ntwo rings tends to fighting, danger to the prince (yuvaraja) and a\nsiege of the town.\n[Cf. tpr—\n5t u]\ntri:\nWhen a planet (Mars, Mercury, Jupiter Venus or Saturn) and\na star are encircled by the halo round the Moon, there will be\nrain within three days, or a war will break out in a month. It would\nbe disastrous to a king, if the lord of his ascendant (at birth) or of\nhis natal sign, or his natal star itself be enclosed within this halo.\n[Gf. ipi—\nTurrsi u]\n^ ^ w^w\ntdxWr^ 5T>f%(TmwTqq>YT II^II\ngpTHg?g?TTTf«rq5T^f t\nqftftcr wmr wftR <n?tT ^ nun\nSaturn being encircled by a halo (round the Moon) destroys\nbase corn such as Priyaitgu, causes stormy rains, and destroys trees\nand agriculturists. Mars inside the halo causes Sufferings to princes\n(or boys), commanders of armies, and armies and trouble from\nfire and weapons. Jupiter in the above situation gives trouble to\nroyal priests, ministers and kings. Mercury inside the halo bestows",
  "metadata": {
    "source": "jyotish_brihat-samhita_m-r-bhat_part-1-of-2_1981.pdf",
    "file_type": ".pdf",
    "file_hash": "f4c82cf5baeeeabcc4dd02e234a68437e6b98d6204707f7d4c3b46dbb79e5a94"
  },
  "chunk_index": 687
}