{
  "id": "doc_20251217_141710_chunk_932",
  "text": "uks.\nHence the house which we have to judge wouk:J be the 41 \" to find\nout whether something Is hidden.\nTo C()nfirm that one is fortunate enough to get it. we have to\njudge the houses 11 and also 8.\n\n362 Encydopeda ofVedicAst!OIOgy: Yout PtOftJSSiOtt\nAt the time of birth the balance of Mercury Oasa was 11 years 6\nmonths ~9 days.\nHe purchased one Prize Bond 5 years ago. E won a prize and\nreceived the cash during his Sun Oasa Moon Bhukti on a Friday when\nMoon was transiting in its own star Sravanam. This is the last draw.\nTherefore he had his success ultimately. though there was long delay\nfor a period of 5 years. First one should know how normally one will\npredict, and then the corrective method.\nC1 ) Sun. &ord of Lagna, was in the gt\" house in the constelation of lord\nof 10 and conjoined with lord of 2 and 11. So Sun has to cause\nOhana Yoga. (Lords of 1. 2 and 11 conjunction Is beneficial).\n(2) It may be said that Moon. lord of 12 in 8 can cause Vipareetha Raja\nyoga.",
  "metadata": {
    "source": "ENCYCLOPEDIA-OF-VEDIC-ASTROLOGY - English.pdf",
    "file_type": ".pdf",
    "file_hash": "ef108f09051687c9017d6d977a95565e27de64804973faa10c496544e09b2cd2"
  },
  "chunk_index": 932
}