{
  "id": "doc_20251217_142523_chunk_329",
  "text": "there will be hike. See the left move then you can predict in India, whether oil prices\nwill go up or not.\nThe left is like daughter in law of rich house hold who huffs and puffs but finally give in\nways of the house hold in reluctant manner.\nIn the long run oil prices will shoot up further. What ever strategy done by the OPEC or by\nthe western nations is bound to make the oil prices shoot up. Hope against hope is sheer\nwaste of time energy and effort.\nIndian economy will not be affected they have good dasa so they manage to come out of it\nsuccessfully.\nA day can come oil can be sold at the rate of 70 dollars a barrel. This can happen when\nSaturn and ketu meets in simha that is between 2006 Sep -2008 Sep.\n The impact of the London bombing. will the global markets\nrecover?\nI saw in the papers that stock markets all over the world were shaken. It is bear grip due to\nLondon bombings.\nFirst this entire situation is only temporary. People will forget as time passes like the",
  "metadata": {
    "source": "mundane-astrology-book_compress.pdf",
    "file_type": ".pdf",
    "file_hash": "b692073ea1891f594624016c0878d7c618cdc387b1e68e1abe54135a3551da0f"
  },
  "chunk_index": 329
}