{
  "id": "doc_20251217_142523_chunk_349",
  "text": "ory but not a boom story. Most of them\nwill have positive story. Ranbaxy Company, which has had major set backs will slowly\nbounce back. India companies will continue to export in a major way. - TRUE\n• Banks- there will be increase computerization in the banks, new models of revenues\nand new products will work out. Many banks will aggressively position themselves on an\nend to end solution. Most of the banks will be in blue or brown which ever is the color of\nthe profit.\n• PSU - the same story of left blocking moves of the government which wants to sell the\nstake to the market will be there. Some flexibility in going for public will be there for\nsome companies. As such no major changes.\n• Oil- markets will bleed. there will be increase in prices with the government taking\ntighter stand. It can even touch 70 dollars per barrel and then it will come down. If you\nhave long terms perspective then this sector is ok. If it is yearly then do not enter the\nsegment or play bearish. - TRUE",
  "metadata": {
    "source": "mundane-astrology-book_compress.pdf",
    "file_type": ".pdf",
    "file_hash": "b692073ea1891f594624016c0878d7c618cdc387b1e68e1abe54135a3551da0f"
  },
  "chunk_index": 349
}