{
  "id": "doc_20251217_142609_chunk_141",
  "text": "y good combination. Ascendant lord Mars\nis in the 11th with Rahu aspected by the Sun (lord of the\n10th) and Ketu. In the Navamsa Mars is in Cancer in\ndebility but the debilitation effect is cancelled. The Sun is\nin Pisces a friendly sign, but is in association with Ketu in\nRasi and with Rahu in Navamsa. The ascendant\nChart No 29.—Born on 18-3-1903 at 12 a.m. (L.T.)\nLat. 15° 32' N., Long. 0° 5h. E.\nBalance of Saturn Dasa at birth : Years 8-11-3.\n\nConcerning the First House 73\nlord and the Sun are both moderate in strength. The subject\nhas taken the characteristics of Mars. He has a handsome\nappearance, broad eyes and thin figure. The faculties are\ngood and brows prominent. The disposition is generous. A\ngood conversationalist with a fertile imagination and\nresourceful nature. The Moon is also free from afflictions.\nThere is much pride in the mental disposition. The native is\na businessman and is well off in life.\nIn physical appearance there is considerable difference",
  "metadata": {
    "source": "raman-how-to-judge-horoscope-1.pdf",
    "file_type": ".pdf",
    "file_hash": "4ed86aac6723314ad2e1d34f43c8d1267ece51d442abd301ea9789980d250404"
  },
  "chunk_index": 141
}