{
  "id": "doc_20251217_142023_chunk_383",
  "text": "for Adhana, but may be applied with advantage\nto the natal chart as well.\nAnother Yoga for Muteness or Imbecility If Jupiter be\ndebilitated, and the Moon be in the Sandhi between two Signs\nor Aihsas. the child born would be either dumb or imbecile.\n\nCONCEPTION AND BIRTH 123\nNow 1 should like you to examine an example of twin-birth.\nThis is the chart of the first of the twins, both female, bom\non 8th July 1951 at 12-45 P.M. The second was born at 2-45\nJup. — — Sun I\n9 Mars 9\nRahu Merc.\n12 9\nVen. 3\n— Ketu 6\nMoon 2\n— — _ Sat. 11\nLag. 6\nP.M. on the same day. The Lagna for the second is the 27th\ndegree of Libra, while that of the first is the 29th degree of\nVirgo. The second one died exactly after a month. The\nMoon in the second is in the 8th degree of Leo, while in the\nfirst she is in the 7th degree. Now look at the details of the\nchart in the light of the rules enunciated above. It wilt also\nshow you how the planetary dispositions do not exactly follow-\nthe rules.",
  "metadata": {
    "source": "jyotish_fundamentals-of-astrology_m-ramakrishna-bhat-1.pdf",
    "file_type": ".pdf",
    "file_hash": "e5a3ea7f4ad4e2c7aeff1f8011d280a31b7a004a2d13ffd77e1158a8d2169388"
  },
  "chunk_index": 383
}