{
  "id": "doc_20251217_141509_chunk_132",
  "text": "snfaf ^^1IHI fflf T^rft | I\ncftfr\n\nfft eft\nfff\nO\n?f eft\nf eft\nf eft\n^r\nT.,f.^. ?t efr\n1\nfteTT 1\n^\nT. ^^Hl % ^int'H ft eft\nI ^TT VJJM* f^RT '^^T ^ ^PT !ei! t>\nt eft\nfteTT\n^t eft\nfanner,\n,\n^Teft\nfteTT\nft eft ^TTeR> ^ft, KHTT ^T 'HHHl^ 3TH\neTOT ^ft t^1 g^Y ^teTT | I\nifteft^niei*f>J'.^t,f^T^Taffa^rpf^ ^f*H Tf^^T^T\n?teTT\nt eft ^\n, ^T, sftT r^* ?teTT 1 1 ^-*!- ^i*if< ff eft\n\nf eft\nff\njf.,r. zrfe ^n*^T ^t ^ft ^TT^F r^fPT ^n^ ( Science )\n1\n1\nf rft vjj]rif, ^j^Kl ^T*TT ^T 'TPT^^^ t\n%\nf\n?n |\nt\nfftrTT\nft ^fi ^nraRpr ^r ^rrfif sftr ^\npft aftr ^rr^9r ^ft fr^r 1 1 fiy^R qf^ S\n., ?r. ^fir ^F^T 5? ^ft jfr^r Ran,\n^\n?f err ^rm^ JRW fe^? TT^T, ftrrftvr\n, f^ffR affT faw^i ft^fT ^ I\n.,^r. irftr ^T*FT ?f ^ft ^mnr fafR, TT^IR ^ ^MH)^ ; TRT\nft Hi ^TTO 3fT^ TRT^T %\nJ\n\n^tsft\n^sr\nsrt\neft ^A^J^iH aftr\n,\ntftar\nf eft\nf eft\n?f eft\nFTT f\nf eft STFeT ^eTT |\n^teTT\nffeft\nff eft ^TeTT\nf eft\nff eft\nfff eft\n\nt ?ft\nfteiT t i\n* <KHHI ft eft\nsfteTT t I\n1T*T!5 ^T ft^TT t I\nfeft\nMU<II>\n?feft\nf eft\n^teTT I I\nT 9H.",
  "metadata": {
    "source": "3- jyotish ratnakar by devki nandan singh (संपूर्ण ज्ञान ).pdf",
    "file_type": ".pdf",
    "file_hash": "040ec60c8792a3f4b51e59ab6b5766ac3617bfcacc8c604f04bf59f5c7b25501"
  },
  "chunk_index": 132
}