{
  "id": "doc_20251217_141710_chunk_855",
  "text": "Aquarius: Using weapons. and fire in different forms (w~ in\nammunition factories and furnaces): thieving; pk>ughing, digging, carrying\nloads on heads and shoutde.I'S, and all sorts of physical wol'k.\nPisces: Weapons (manufacture. use. trade): water (watef supply\nworks. shipping, boats, etc.): dealing in things used for sex. medici'les\nfor abortion and obscene literature; trade in horses\nlndiciJtions by piMets endowed with all points of Slrength when\nthey ~ppen to be lords of he 1(/11 or lords of NavamSQS of the owners\nof the l(f\"\nA Pl~net indicates a lar~ number of jobs of whi<:h only a seJected\nfew are shown against each.\nThe Sun: H!ghty authoritative jobs in the Government, Forest\nDepartment, MuniCipal Corporations. Civil Engineering (P.W.O.), MediCine\nwork connected with chemicals, architectural work, and work with\nmetals, (buSiness may also be included).\nThe Moon: Agriculture. communications (railways and other land\ntransports). trade in objects got from water. dairy farms.",
  "metadata": {
    "source": "ENCYCLOPEDIA-OF-VEDIC-ASTROLOGY - English.pdf",
    "file_type": ".pdf",
    "file_hash": "ef108f09051687c9017d6d977a95565e27de64804973faa10c496544e09b2cd2"
  },
  "chunk_index": 855
}