{
  "id": "doc_20251217_141853_chunk_63",
  "text": "HeeHeûen\nefmLele neskeÀj ®elegLe& YeeJe keÀes osKeW Gleves mebK³ekeÀ De®ís JeenveeW keÀe veeMe neslee nw ~\nSsmee og³eexie nesves Hej mece³eevegmeej Jeenve nsleg MegYe Meevl³eLe& ke=Àl³e keÀe DeeosMe\nefJeÜeveeW keÀes keÀjvee ®eeefnS ~~ 10 ~~\n\n32\nHeáeceYeeJe HeÀueõ\nefJeÐeemLeeveeefOeHees Jee yegOeieg©meefnleM®esled ef$ekesÀ Jele&ceevees\nefJeÐenervees vej: m³eeoLe veJeceefvepe#es$e keÀsvês<eg leÜeved ~\nyeeuelJeb Je=×lee Jee ³eefo ieievemeoeb pevcekeÀeues leoe m³eeled\nÒe%eeceevÐeb vejeCeeceLe ³eefo efJenie: mJe#e&iees oes<eËlm³eeled ~~ 11 ~~\nDevJe³e:ö efJeÐeemLeeveeefOeHees Jee yegOeieg© meefnle: (He_®ecesMe:) ef$ekesÀ\nJele&ceevees vej: efJeÐeenervees m³eeled ~ DeLe veJeceefvepe#es$e kesÀvês<eg (He_®ecesMe:) ®esled\nleÜeve YeJeefle ~ ³eefo pevcekeÀeues ieievemeoeb yeeuelJeb Je=×lee Jee leoe vejeCeeb\nÒe%eeceevÐeb m³eeled ~ DeLe ³eefo efJenie: mJe#e&ie: (®esÊeoe) oes<eËled m³eeled ~~ 11 ~~\nDeLe Heáece YeeJeHeÀueb efJeJe#egefve&©Hee³esve efJeÐeeyegef×³eesieeveen ~ efJeÐesefle ~",
  "metadata": {
    "source": "Jataka-Alankar - Hindi.pdf",
    "file_type": ".pdf",
    "file_hash": "b11d368369b4403d20f3042032e1fe6f7df0394e35a6b53112f2de19b5fd2b62"
  },
  "chunk_index": 63
}