{
  "id": "doc_20251217_142310_chunk_297",
  "text": "sweet\nspeaker, be a minister and be highly learned.\nIf Jupiter is in Leo and is aspected by Venus, the native will be dear to females, be fortunate, will\nreceive royal honours and be very strong.\n89\n\nIf Jupiter is in Leo and is aspected by Saturn, one will be garrulous, be an eloquent speaker, be\ndevoid of happiness, be sharp and will have mean children and mean wife.\n55-60. JUPITER IN OWN HOUSE AND IN ASPECT TO OTHERS. If Jupiter is posited in\nSagittarius/Pisces at birth and is aspected by the Sun, the native will be inimical to the king\nand will be miserable being bereft of wealth and relatives.\nIf Jupiter is posited in Sagittarius/Pisces and is aspected by the Moon, the native will enjoy many\nkinds of happiness, be very fortunate in respect of wife and will have the pride of honour,\nwealth and possessions.\nIf Jupiter is posited in Sagittarius/Pisces and is aspected by Mars, one will be injured in war, be\ncruel, will cause torture, will harm others and will lose children.",
  "metadata": {
    "source": "kalyana-varma-saravali.pdf",
    "file_type": ".pdf",
    "file_hash": "39c2ba173fa4c9ca019b47aee35eb3d9c19f61e61f5cfea2f54eb50e0d244f58"
  },
  "chunk_index": 297
}