{
  "id": "doc_20251217_141947_chunk_87",
  "text": "he author shows his proficiency in that branch also.7 His descrip-\ntion of the preparation and benefits of tooth powder and chewing\nbetel leaves would bear repetition.6 His reference to Pranayama and\nthe process of the soul's experiencing pleasure and pain confirms\nour belief in his acquaintance with PdtahjalaYogVLSVttas, Sdmkhya\nand other systems of philosophy.9\n1. Vide LXXIV. 13.\n2. „ XLVHI. 71, LVI. 2.\n3. LX. 22\n4! LXXVI. 1; LXXV1I1. 23. 24, 26.\n5. „ XLVltl. 52.\n6. „ LIV.\n7. XXIX. 2, XLVT1T. 39-42; XL1II. 15; LIV; LV. 3, 4, 10, ] I; LX. 8.\n8. „ LXXVU. 31-33; 35-37.\n9. „ XGV. 62; LXXV. 3.\n\nIntroduction XXXV\nThe author shows his intimate knowledge of culinary art also,\nas he refers several times to sweets and other tasty edibles like\n^r, srcfsft, -rm, etc.1 His knowl-\nedge of ornithology is borne out by his detailed treatment of various\nspecies of birds in connection with auguries. In this connection we\nare tempted to refer again to the wholesome political tradition",
  "metadata": {
    "source": "jyotish_brihat-samhita_m-r-bhat_part-1-of-2_1981.pdf",
    "file_type": ".pdf",
    "file_hash": "f4c82cf5baeeeabcc4dd02e234a68437e6b98d6204707f7d4c3b46dbb79e5a94"
  },
  "chunk_index": 87
}