{
  "id": "doc_20251217_141756_chunk_494",
  "text": "und out by the Mooo's positioo. 1be method of 11. NII/!.tlab or COlUUmmatlon CerelNtJlly ..- There Ibould\n'.\ncounting the lunar days il aiven io the earlier chapters. be no planets io the 8th. Sunday. Sat~rda)' a~d Tueaday:are\nTake the number of lunar daYI rrom tbe first oC each bad. TauruI, Gemini, Cancer, Leo, VlflO, Libra, AquanUl.\nlunar month. the number of weekdays from Sunday, the Slgittarius aDd Pisces arc good. New Moon day. Full,\n,\n•\n\n'44 Hindu Predictive AltrOJoay Miuburtba Of Ejection 2. ..\"\nMOOD day, tb~ 14tb, 6th. 8tb and 4thd~ys oftbc lunar month constellations Bharani, Krittika, Aridra, Aslesba, Ma\"kba,\nmus~ ,be avoided. The constellations Satabhisba, Hasta. Pubba, Visakba, Jyeshta, Moola, Poorvashadha. SatabbiSba'\nRablDl, Sravana, Anutadba, SW8ti, UUar., Uttarashadba aDd Poorvabhadra are evil constellations and tbis ceremony\nMoola and Ultabhadra arc good. • Plust be performed in anyone of the remaining IS constella\n12. Nome-Glvin Nomakarona 0 a New-born Child.",
  "metadata": {
    "source": "Hindu Predictive Astrology ( PDFDrive ).pdf",
    "file_type": ".pdf",
    "file_hash": "480b97138a612533982d548e64949873d02f7802bd4ee9b2b7e21c080149fbe8"
  },
  "chunk_index": 494
}