{
  "id": "doc_20251217_141710_chunk_841",
  "text": "ng, the lot\" house Is occupied by Mercury. The native Is\na university teacher. Lord of the gt\" (publication). jupiter. is in the\n7~~'~ house aspealng Lagna. He supplements his income by writing\nbooks. Venus, lord of the 110\\, is in the 11111 • This assures steady\nflow of income.\n4. Kumbha rising, the lOib house is occupied with Ju pitet lord of the\nnt\".\nIt is aspected by Satum from the 41 \" house. The native is a\nconfectioner. He supplements his income through speculation. Lord\n111 st\"\nof the 10 • Mars. is in the house,\nPredicting Means ot Livelihood\nIn this age tl'le ma<:hine is written large in the horoscope of man.\nMechanical progress. scientific ingenuity and advanced technolOgy have\nlberated much of the energies of man leading to colossal aeflievements.\nRuthless competition, commerdatism, advertising and salesmanship,\nexcessive materialistic activity of mechanised industry and a hundred\nand odd economic, social and political superstructures of life have exposed",
  "metadata": {
    "source": "ENCYCLOPEDIA-OF-VEDIC-ASTROLOGY - English.pdf",
    "file_type": ".pdf",
    "file_hash": "ef108f09051687c9017d6d977a95565e27de64804973faa10c496544e09b2cd2"
  },
  "chunk_index": 841
}