{
  "id": "doc_20251217_142621_chunk_39",
  "text": "a\nMantra\noṁ hanumate namaḥ,\noṁ, hauṃ, hsphreṃ, khphreṃ, hsauṃ, hskhreṃ, hsauṃ, oṁ\n61\nAghori.it\n\noṁ vājrakāya vājratunda kapila pingala kālavadāno\nurdhavākesha mahābala ratkamukha tadijivha mahāraudra\ndraṃṣṭokaṭa mahākarālini mahā dradh prahār\nlankeshvarasetuvandha shailapravaha gaganacara e ho hī |\nbhagavāna mahābala parākraṃ bhairavo jhāpayati e ho hī\nmahāraudra dirgha langalena amuk veṣṭaya veṣṭaya jambhaya\njambhaya khana khana vaite huṃ phat ||\noṁ aiṃ bhrīṃ hanumate rāmdutāya namaḥ ||\noṁ huṃ hanumate raudratāmakhaya huṃ phat ||\nMARUTI YANTRA\n62\nAghori.it\n\nMantra\noṁ namo bhagavate ājjaneyāya mahā balāya svāhā\noṁ śrī rāmduta pavanaputa dega calā jaise rāmacandra ke\nkoja saṁvāre kāja mero savāro\nRAMA YANTRA\n9 16 5 4\n7 2 11 14\n12 13 8 1\n6 3 10 15\nGARAPAL YANTRA\nॐ ॐ ॐ ॐ\nॐ ॐ ॐ ॐ\nह्रीं ह्रीं ह्रीं ह्र ीं\nह्रीं ह्रीं ह्रीं ह्र ीं\n63\nAghori.it\n\nNavgraha Yantra\nthe yantra of the nine planets\nRahu and Ketu are the lunar knots.\n64\nAghori.it\n\nSURYA YANTRA\n6 32 3 34 35 1\n7 11 27 28 8 30",
  "metadata": {
    "source": "yantras-heavenly-geometries-aghori.pdf",
    "file_type": ".pdf",
    "file_hash": "1f1a0122f796e6bf92cc75f486c1b22a14ab64180f7aafb24b01e22c0ddbf0f0"
  },
  "chunk_index": 39
}