{
  "id": "doc_20251217_141853_chunk_125",
  "text": "eowJe ~~\nveJeceYeeJeHeleer efjHegjvOe´ûees veJeceYeb efjHeg¢ä³egleb leLee ~\n³eefo leoe ve ®e Oece&jlees vej: MegYeKeiewjLe Oece&jlees vej: ~~\nDeyeuesçefHe MegYes Kesìs Yeei³emLes Oeeefce&keÀer vej: ~\nMegYeJeie& ³egles Yeei³es MegYekeÀcee&³eLeeçv³eLee ~~\nFl³eeefo ef®evlee efJeOes³ee, le$een peelekeÀmeejeJeueerkeÀej: -\nnesjsvoesye&ue³eesieeÐees oMecemlelmJeYeeJepeb keÀce& ~\nlem³eeOegHelesM®e leLee Je=ef×%ex³ee leLee neefve: ~~\noMeces ve#e$eHeefleue&iveelHeg©<em³e ³em³e mecYeJeefle ~\nmeJee&jcYees YeJeefle efn efJeefveefo&MesÊem³e peelem³e ~~\npeelekeÀmeejsö mJemLes Keies Keue³egles Keuepes veJeebMes\nmJees®®e#e&ies mJeYeJeves megKeJe=Êe³e: m³eg: ~\nveer®eeefjYeeJe: ie=niesçuHemegKeeuHeHegC³ees\noemeesHe®eej:Ye=lekeÀeveg®ejeM®e oemeer: ~~\n\n57\nOece&YeeJes MegYe#es$es MegYe¢äs megkeÀce&ke=Àled ~\nHeeHesef#eles HeeHekeÀcee& mJeeceer ¢äs leg ceO³ece: ~~\nJewÐee: Hegjesefnlee: Meem$emce=efle%ee JeáekeÀe veje: ~\npee³evles keÀce&iew: HeeHew: meewc³eûenefvejer#elew: ~~",
  "metadata": {
    "source": "Jataka-Alankar - Hindi.pdf",
    "file_type": ".pdf",
    "file_hash": "b11d368369b4403d20f3042032e1fe6f7df0394e35a6b53112f2de19b5fd2b62"
  },
  "chunk_index": 125
}