{
  "id": "doc_20251217_141823_chunk_100",
  "text": "of loss of child at the age of 56 will come to pass.\n24-32. Number of Children. There will be 10 sons, if Bandhu Bhava and Ari\nBhava are occupied by malefics, while Putr‟s Lord is in deep exaltation,\njoining Lagn‟s Lord, as Guru is with another benefic. Nine will be the\nnumber of sons, that one will beget, if Guru is in deep exaltation, as Rahu\nis with Dhan‟s Lord and Dharm is occupied by its own Lord. There will be\neight sons, if Guru is in Putr, or Dharm Bhava, while Putr‟s Lord is endowed\nwith strength and Dhan‟s Lord is in Karm Bhava. Śani in Dharm Bhava,\nwhile Putr‟s Lord is in Putr itself, gives 7 sons, out of which twins will be\nborn twice. If Putr‟s Lord is in Putr in Yuti with Dhan‟s Lord, there will be\nbirth of 7 sons, out of which 3 will pass away. Only one son is denoted, if\nth\nthere be a malefic in Putr Bhava, while Guru is in the 5 from Śani, or vice\nth\nversa. If Putr Bhava has a malefic in it, or, if Śani is in the 5 from Guru, the",
  "metadata": {
    "source": "instapdf.in-brihat-parashara-hora-shastra-book-710.pdf",
    "file_type": ".pdf",
    "file_hash": "40f12d7c6b42a7625d36bc1cc38576427f4c64f41a8f1353f4945a603a4397ba"
  },
  "chunk_index": 100
}