{
  "id": "doc_20251217_142523_chunk_98",
  "text": "l continue to have a successful married life.\nHema Malini’s children\n*5th lord Mars in its own house.\n*From Chandra lagna 5th lord in female sign.\n*From Karakamsha lagna the 5th lord is in the Venus.\nShe has female children due to these combinations. Her children will be intelligent,\nand moderately successful. It will be impossible for them to replicate the stardom her\nmother had acquired.\nHema Malini’s profession\nFrom lagna 10th lord is placed in the 5th house, and from other lagnas too the 10th\nlord is strongly placed.\nShe will be remembered as one of the greatest actresses of Hindi Cinema.\nFuture of Hema Malini\n*She had her come back in Bhagwan, exactly when Saturn was transiting her 11th\nhouse. *She will continue to act in movies. Between Sept 2004 and Sept 2006, she will\n\nhave few success stories on the silver screen.\nBal Thackeray – The uncrowned King! –\nFriday, 30 January, 2004, 11:04\nThe roaring tiger of Maharashtra Balasaheb Thackeray is as powerful as a King in\nmodern terms.",
  "metadata": {
    "source": "mundane-astrology-book_compress.pdf",
    "file_type": ".pdf",
    "file_hash": "b692073ea1891f594624016c0878d7c618cdc387b1e68e1abe54135a3551da0f"
  },
  "chunk_index": 98
}