{
  "id": "doc_20251217_141756_chunk_210",
  "text": "and the 7tbtlouses; or\nand renunciation of the world; and Arishlayoga-series of\nlord of the 9th is powerful and Venus and lord of Ascendant\nmisfortunes orthe most baneful oature. There are thousands\narc in quadrants from Jupiter-Landed estates, free from\nof lucb yogas given in the original Sanskrit works and tbeir\nencumbrance. high family traditions, eulled soul, courageous.\nreproduction bere would mean firstly a great slrain on tbe\nexpert in sciences and artl, long lived, free from lOY kind of\ncomprebending powers of tbe reader and secondly, increase\ndiseases.\nof tbe bulk of the book beyond proportioo. The results\n,-\n\n'I\n108 Hind\\l Predictive AltrolOC) Some Special YOIIlS 109\n->\nS. Sorado Yoga.- Jupiler in a trinc from the MOOD, and 13. Vas; Y08a.- Planets in the ·12th (rom tbe Sun_\nMars in tdoe to Mercury or Jupiter in the 11th from Mercury JnOueDiiat'~ltb and wealthy.\nor lord of tbe 10th occupies the 5th, Mercury in a quadrant 4-1~t . tffJi XI\".a.",
  "metadata": {
    "source": "Hindu Predictive Astrology ( PDFDrive ).pdf",
    "file_type": ".pdf",
    "file_hash": "480b97138a612533982d548e64949873d02f7802bd4ee9b2b7e21c080149fbe8"
  },
  "chunk_index": 210
}